vininfo/__init__.py
vininfo/assemblers.py
vininfo/brands.py
vininfo/cli.py
vininfo/common.py
vininfo/exceptions.py
vininfo/toolbox.py
vininfo/utils.py
vininfo/details/__init__.py
vininfo/details/_base.py
vininfo/details/avtovaz.py
vininfo/details/bajaj.py
vininfo/details/dafra.py
vininfo/details/nissan.py
vininfo/details/opel.py
vininfo/details/renault.py
vininfo/dicts/__init__.py
vininfo/dicts/bodies.py
vininfo/dicts/countries.py
vininfo/dicts/regions.py
vininfo/dicts/wmi.py
vininfo-1.9.2.dist-info/METADATA
vininfo-1.9.2.dist-info/WHEEL
vininfo-1.9.2.dist-info/entry_points.txt
vininfo-1.9.2.dist-info/licenses/LICENSE
vininfo-1.9.2.dist-info/RECORD
