Metadata-Version: 2.4
Name: vininfo
Version: 1.9.2
Summary: Extracts useful information from Vehicle Identification Number (VIN)
Project-URL: Homepage, https://github.com/idlesign/vininfo
Author-email: Igor Starikov <idlesign@yandex.ru>
License-Expression: BSD-3-Clause
License-File: LICENSE
Keywords: vehicles,vin
Requires-Python: >=3.10
Provides-Extra: cli
Requires-Dist: click; extra == 'cli'
